psarps/__init__.py
psarps/__main__.py
psarps/lib.py
psarps-0.1.3.dist-info/METADATA
psarps-0.1.3.dist-info/WHEEL
psarps-0.1.3.dist-info/entry_points.txt
psarps-0.1.3.dist-info/licenses/LICENSE
psarps-0.1.3.dist-info/RECORD
