Metadata-Version: 2.4
Name: PSARPS
Version: 0.1.3
Summary: Get metadata about Planet Scope ARPS satellite imagery
License-File: LICENSE
Requires-Python: >=3.10
Requires-Dist: cyclopts>=3.16.0
Requires-Dist: geopy>=2.4.1
Requires-Dist: proj>=0.2.0
Requires-Dist: pyproj>=3.7.1
Requires-Dist: rasterio>=1.4.3
Requires-Dist: requests>=2.32.3
Requires-Dist: rich>=14.0.0
Requires-Dist: shapely>=2.1.0
